losspy/__init__.py
losspy/pixel_based/__init__.py
losspy/pixel_based/cross_entropy.py
losspy/pixel_based/mae_mse.py
losspy/pixel_based/total_variation.py
losspy/region_based/__init__.py
losspy/region_based/dice_iou.py
losspy/region_based/hel.py
losspy/region_based/ssim.py
losspy/utils/__init__.py
losspy/utils/convert_onehot.py
losspy/utils/misc.py
losspy-0.1.1.dist-info/LICENSE
losspy-0.1.1.dist-info/METADATA
losspy-0.1.1.dist-info/WHEEL
losspy-0.1.1.dist-info/top_level.txt
losspy-0.1.1.dist-info/RECORD
